robotcode/repl/__init__.py
robotcode/repl/__version__.py
robotcode/repl/base_interpreter.py
robotcode/repl/cli.py
robotcode/repl/console_interpreter.py
robotcode/repl/hooks.py
robotcode/repl/py.typed
robotcode/repl/run.py
robotcode/repl/Repl/__init__.py
robotcode/repl/Repl/repl.py
robotcode_repl-2.0.1.dist-info/METADATA
robotcode_repl-2.0.1.dist-info/WHEEL
robotcode_repl-2.0.1.dist-info/entry_points.txt
robotcode_repl-2.0.1.dist-info/RECORD
